bizflow_db_helper/__init__.py
bizflow_db_helper/db_helper.py
bizflow_db_helper-2.0.0.dist-info/licenses/LICENSE
bizflow_db_helper-2.0.0.dist-info/METADATA
bizflow_db_helper-2.0.0.dist-info/WHEEL
bizflow_db_helper-2.0.0.dist-info/top_level.txt
bizflow_db_helper-2.0.0.dist-info/RECORD
