Metadata-Version: 2.4
Name: bizflow-db-helper
Version: 2.0.0
Summary: A comprehensive database helper library for Oracle, SQL Server, and PostgreSQL with support for data import/export operations
Author-email: littlekeixi <littlekeixi@example.com>
Project-URL: Homepage, https://github.com/littlekeixi/dbhelper
Project-URL: Bug Reports, https://github.com/littlekeixi/dbhelper/issues
Project-URL: Source, https://github.com/littlekeixi/dbhelper
Keywords: database,oracle,sql-server,postgresql,pandas,data-import,data-export
Classifier: Development Status :: 4 - Beta
Classifier: Intended Audience :: Developers
Classifier: License :: OSI Approved :: MIT License
Classifier: Operating System :: OS Independent
Classifier: Programming Language :: Python :: 3
Classifier: Programming Language :: Python :: 3.8
Classifier: Programming Language :: Python :: 3.9
Classifier: Programming Language :: Python :: 3.10
Classifier: Programming Language :: Python :: 3.11
Classifier: Programming Language :: Python :: 3.12
Classifier: Topic :: Database
Classifier: Topic :: Software Development :: Libraries :: Python Modules
Requires-Python: >=3.8
License-File: LICENSE
Requires-Dist: oracledb>=1.0.0
Requires-Dist: pandas>=1.3.0
Requires-Dist: bcpy>=0.1.0
Requires-Dist: sqlalchemy>=1.4.0
Requires-Dist: numpy>=1.20.0
Dynamic: license-file
